nonebot_plugin_pixivbot_onebot_v11/__init__.py
nonebot_plugin_pixivbot_onebot_v11/config.py
nonebot_plugin_pixivbot_onebot_v11/handler/__init__.py
nonebot_plugin_pixivbot_onebot_v11/handler/poke.py
nonebot_plugin_pixivbot_onebot_v11/protocol_dep/__init__.py
nonebot_plugin_pixivbot_onebot_v11/protocol_dep/authenticator.py
nonebot_plugin_pixivbot_onebot_v11/protocol_dep/post_dest.py
nonebot_plugin_pixivbot_onebot_v11/protocol_dep/postman.py
nonebot_plugin_pixivbot_onebot_v11-1.5.1.dist-info/LICENSE
nonebot_plugin_pixivbot_onebot_v11-1.5.1.dist-info/WHEEL
nonebot_plugin_pixivbot_onebot_v11-1.5.1.dist-info/METADATA
nonebot_plugin_pixivbot_onebot_v11-1.5.1.dist-info/RECORD
