Metadata-Version: 2.1
Name: nonebot-plugin-pixivbot-onebot-v11
Version: 1.5.1
Summary: Nonebot Plugin PixivBot (Onebot V11)
Home-page: https://github.com/ssttkkl/nonebot-plugin-pixivbot-onebot-v11
License: MIT
Author: ssttkkl
Author-email: huang.wen.long@hotmail.com
Requires-Python: >=3.9,<4.0
Classifier: License :: OSI Approved :: MIT License
Classifier: Programming Language :: Python :: 3
Classifier: Programming Language :: Python :: 3.9
Classifier: Programming Language :: Python :: 3.10
Classifier: Programming Language :: Python :: 3.11
Requires-Dist: nonebot-adapter-onebot (>=2.1.1,<3.0.0)
Requires-Dist: nonebot2 (>=2.0.0rc1,<3.0.0)
Project-URL: Repository, https://github.com/ssttkkl/nonebot-plugin-pixivbot-onebot-v11
